pymupdf4llm_enchanced_mcp/main.py
pymupdf4llm_enchanced_mcp-0.1.0.dist-info/METADATA
pymupdf4llm_enchanced_mcp-0.1.0.dist-info/WHEEL
pymupdf4llm_enchanced_mcp-0.1.0.dist-info/entry_points.txt
pymupdf4llm_enchanced_mcp-0.1.0.dist-info/licenses/LICENSE
pymupdf4llm_enchanced_mcp-0.1.0.dist-info/RECORD
